mmaing_aesop/__init__.py
mmaing_aesop/ensemble.py
mmaing_aesop/model.py
mmaing_aesop/plot.py
mmaing_aesop/utils.py
mmaing_aesop-0.1.8.dist-info/METADATA
mmaing_aesop-0.1.8.dist-info/WHEEL
mmaing_aesop-0.1.8.dist-info/top_level.txt
mmaing_aesop-0.1.8.dist-info/RECORD
