Metadata-Version: 2.4
Name: mmaing_aesop
Version: 0.1.8
Summary: Mixed Model of Artificial Intelligence and Next-Generation for outbreak detection.
Author-email: Dérick Borges <seudemail@example.com>
License: Apache-2.0
Project-URL: Homepage, https://pypi.org/project/mmaing_aesop/
Requires-Python: >=3.8
Requires-Dist: pandas
Requires-Dist: numpy
Requires-Dist: scikit-learn
Requires-Dist: pyod
Requires-Dist: matplotlib
Requires-Dist: scipy
